gwx_payment/__init__.py
gwx_payment/abstract_payment_service.py
gwx_payment/provider_service.py
gwx_payment/config/__init__.py
gwx_payment/config/gwx_payment_config.ini
gwx_payment/exceptions/__init__.py
gwx_payment/exceptions/stripe_error_exception.py
gwx_payment/exceptions/stripe_invalid_request_error_exception.py
gwx_payment/lib/__init__.py
gwx_payment/lib/config_parser_service.py
gwx_payment/lib/service_locator_service.py
gwx_payment/providers/__init__.py
gwx_payment/providers/stripe_service.py
gwx_payment-0.0.1.dist-info/METADATA
gwx_payment-0.0.1.dist-info/WHEEL
gwx_payment-0.0.1.dist-info/top_level.txt
gwx_payment-0.0.1.dist-info/RECORD
