Metadata-Version: 2.1
Name: gwx-payment
Version: 0.0.1
Summary: Payment gateway integration bridge for python, specifically flask based applications.
Home-page: https://bitbucket.org/groworxdigitalengineering/gwx-payment/src/master
Author: Jerric Calosor
Author-email: jerric.calosor@groworx.com.au
License: UNKNOWN
Platform: UNKNOWN
Classifier: Programming Language :: Python :: 3
Classifier: License :: OSI Approved :: MIT License
Classifier: Operating System :: OS Independent
Requires-Python: >=3.7
